{
	"format_version": "1.12.0",
	"minecraft:geometry": [
		{
			"description": {
				"identifier": "geometry.jupiter",
				"texture_width": 256,
				"texture_height": 256,
				"visible_bounds_width": 20,
				"visible_bounds_height": 20,
				"visible_bounds_offset": [0, 1.5, 0]
			},
			"bones": [
				{
					"name": "root",
					"pivot": [0, 0, 0]
				},
				{
					"name": "planet",
					"parent": "root",
					"pivot": [0, 15.91824, -0.02673],
					"cubes": [
						{"origin": [23, -5, 22], "size": [2, 30, 2], "uv": [0, 0]},
						{"origin": [9, 9, 22], "size": [30, 2, 2], "uv": [0, 0]},
						{"origin": [23, 9, 8], "size": [2, 2, 30], "uv": [0, 0]},
						{"origin": [20, -6, 19], "size": [8, 1, 8], "uv": [206, 108]},
						{"origin": [18, -5, 17], "size": [12, 1, 12], "uv": [0, 0]},
						{"origin": [16, -4, 15], "size": [16, 1, 16], "uv": [0, 0]},
						{"origin": [15, -2, 14], "size": [18, 2, 18], "uv": [0, 0]},
						{"origin": [14, 0, 13], "size": [20, 20, 20], "uv": [0, 0]},
						{"origin": [16, -4, 15], "size": [16, 1, 16], "uv": [0, 0]},
						{"origin": [16, 23, 15], "size": [16, 1, 16], "uv": [0, 0]},
						{"origin": [15, 20, 14], "size": [18, 2, 18], "uv": [0, 0]},
						{"origin": [15, 22, 15], "size": [1, 1, 16], "uv": [0, 0]},
						{"origin": [14, 20, 14], "size": [1, 2, 18], "uv": [0, 0]},
						{"origin": [13, 20, 15], "size": [1, 1, 16], "uv": [0, 0]},
						{"origin": [12, 19, 14], "size": [2, 1, 18], "uv": [0, 0]},
						{"origin": [11, 18, 15], "size": [1, 1, 16], "uv": [0, 0]},
						{"origin": [36, 18, 15], "size": [1, 1, 16], "uv": [0, 0]},
						{"origin": [34, 19, 14], "size": [2, 1, 18], "uv": [0, 0]},
						{"origin": [34, 20, 15], "size": [1, 1, 16], "uv": [0, 0]},
						{"origin": [33, 20, 14], "size": [1, 2, 18], "uv": [0, 0]},
						{"origin": [32, 22, 15], "size": [1, 1, 16], "uv": [0, 0]},
						{"origin": [32, -3, 15], "size": [1, 1, 16], "uv": [0, 0]},
						{"origin": [33, -2, 14], "size": [1, 2, 18], "uv": [0, 0]},
						{"origin": [34, -1, 15], "size": [1, 1, 16], "uv": [0, 0]},
						{"origin": [34, 0, 15], "size": [2, 1, 16], "inflate": 0.01, "uv": [0, 0]},
						{"origin": [36, 1, 15], "size": [1, 1, 16], "uv": [0, 0]},
						{"origin": [11, 1, 15], "size": [1, 1, 16], "uv": [0, 0]},
						{"origin": [12, 0, 14], "size": [2, 1, 18], "uv": [0, 0]},
						{"origin": [13, -1, 15], "size": [1, 1, 16], "uv": [0, 0]},
						{"origin": [14, -2, 14], "size": [1, 2, 18], "uv": [0, 0]},
						{"origin": [15, -3, 15], "size": [1, 1, 16], "uv": [0, 0]},
						{"origin": [18, 24, 17], "size": [12, 1, 12], "uv": [0, 0]},
						{"origin": [28, -6, 20], "size": [1, 1, 6], "uv": [0, 0]},
						{"origin": [19, -6, 20], "size": [1, 1, 6], "uv": [0, 0]},
						{"origin": [19, 25, 20], "size": [1, 1, 6], "uv": [0, 0]},
						{"origin": [28, 25, 20], "size": [1, 1, 6], "uv": [0, 0]},
						{"origin": [20, 25, 19], "size": [8, 1, 8], "uv": [75, 27]},
						{"origin": [21, 25, 27], "size": [6, 1, 1], "uv": [0, 0]},
						{"origin": [22, 22, 34], "size": [4, 1, 1], "uv": [0, 0]},
						{"origin": [22, 21, 35], "size": [4, 1, 1], "uv": [173, 29]},
						{"origin": [22, 21, 10], "size": [4, 1, 1], "uv": [0, 0]},
						{"origin": [22, 22, 11], "size": [4, 1, 1], "uv": [5, 19]},
						{"origin": [22, -3, 11], "size": [4, 1, 1], "uv": [0, 2]},
						{"origin": [22, -2, 10], "size": [4, 1, 1], "uv": [0, 0]},
						{"origin": [22, -2, 35], "size": [4, 1, 1], "uv": [0, 0]},
						{"origin": [22, -3, 34], "size": [4, 1, 1], "uv": [6, 19]},
						{"origin": [21, 25, 18], "size": [6, 1, 1], "uv": [0, 0]},
						{"origin": [21, -6, 18], "size": [6, 1, 1], "uv": [0, 0]},
						{"origin": [21, -6, 27], "size": [6, 1, 1], "uv": [0, 0]},
						{"origin": [8, 6, 19], "size": [1, 8, 8], "uv": [0, 0]},
						{"origin": [9, 4, 17], "size": [1, 12, 12], "uv": [0, 0]},
						{"origin": [10, 2, 15], "size": [1, 16, 16], "uv": [0, 0]},
						{"origin": [12, 1, 14], "size": [2, 18, 18], "uv": [0, 0]},
						{"origin": [37, 2, 15], "size": [1, 16, 16], "uv": [0, 4]},
						{"origin": [34, 0, 14], "size": [2, 19, 18], "uv": [0, 0]},
						{"origin": [38, 4, 17], "size": [1, 12, 12], "uv": [0, 0]},
						{"origin": [8, 14, 20], "size": [1, 1, 6], "uv": [0, 0]},
						{"origin": [8, 5, 20], "size": [1, 1, 6], "uv": [0, 0]},
						{"origin": [39, 5, 20], "size": [1, 1, 6], "uv": [0, 0]},
						{"origin": [36, -2, 21], "size": [1, 1, 4], "uv": [0, 0]},
						{"origin": [35, -3, 21], "size": [1, 1, 4], "uv": [0, 0]},
						{"origin": [35, 22, 21], "size": [1, 1, 4], "uv": [0, 0]},
						{"origin": [36, 21, 21], "size": [1, 1, 4], "uv": [0, 0]},
						{"origin": [11, 21, 21], "size": [1, 1, 4], "uv": [0, 3]},
						{"origin": [12, 22, 21], "size": [1, 1, 4], "uv": [0, 0]},
						{"origin": [12, -3, 21], "size": [1, 1, 4], "uv": [0, 0]},
						{"origin": [11, -2, 21], "size": [1, 1, 4], "uv": [0, 0]},
						{"origin": [38, 3, 19], "size": [1, 1, 8], "uv": [0, 0]},
						{"origin": [38, 16, 19], "size": [1, 1, 8], "uv": [0, 0]},
						{"origin": [9, 16, 19], "size": [1, 1, 8], "uv": [0, 0]},
						{"origin": [10, 18, 17], "size": [1, 1, 12], "uv": [0, 0]},
						{"origin": [10, 1, 17], "size": [1, 1, 12], "uv": [0, 0]},
						{"origin": [37, 1, 17], "size": [1, 1, 12], "uv": [0, 0]},
						{"origin": [37, 18, 17], "size": [1, 1, 12], "uv": [0, 0]},
						{"origin": [32, 23, 17], "size": [1, 1, 12], "uv": [0, 0]},
						{"origin": [15, 23, 17], "size": [1, 1, 12], "uv": [0, 0]},
						{"origin": [15, -4, 17], "size": [1, 1, 12], "uv": [0, 0]},
						{"origin": [14, -3, 17], "size": [1, 1, 12], "uv": [0, 0]},
						{"origin": [13, -2, 17], "size": [1, 1, 12], "uv": [0, 7]},
						{"origin": [12, -1, 17], "size": [1, 1, 12], "uv": [0, 0]},
						{"origin": [11, 0, 17], "size": [1, 1, 12], "uv": [2, 7]},
						{"origin": [11, 19, 17], "size": [1, 1, 12], "uv": [0, 0]},
						{"origin": [12, 20, 17], "size": [1, 1, 12], "uv": [3, 6]},
						{"origin": [13, 21, 17], "size": [1, 1, 12], "uv": [10, 10]},
						{"origin": [14, 22, 17], "size": [1, 1, 12], "uv": [0, 0]},
						{"origin": [33, 22, 17], "size": [1, 1, 12], "uv": [0, 0]},
						{"origin": [34, 21, 17], "size": [1, 1, 12], "uv": [0, 0]},
						{"origin": [35, 20, 17], "size": [1, 1, 12], "uv": [0, 0]},
						{"origin": [36, 19, 17], "size": [1, 1, 12], "uv": [5, 5]},
						{"origin": [36, 0, 17], "size": [1, 1, 12], "uv": [0, 4]},
						{"origin": [35, -1, 17], "size": [1, 1, 12], "uv": [0, 8]},
						{"origin": [34, -2, 17], "size": [1, 1, 12], "uv": [2, 2]},
						{"origin": [33, -3, 17], "size": [1, 1, 12], "uv": [0, 0]},
						{"origin": [32, -4, 17], "size": [1, 1, 12], "uv": [0, 0]},
						{"origin": [9, 3, 19], "size": [1, 1, 8], "uv": [0, 0]},
						{"origin": [17, 24, 19], "size": [1, 1, 8], "uv": [0, 0]},
						{"origin": [30, 24, 19], "size": [1, 1, 8], "uv": [0, 0]},
						{"origin": [30, -5, 19], "size": [1, 1, 8], "uv": [0, 0]},
						{"origin": [17, -5, 19], "size": [1, 1, 8], "uv": [0, 0]},
						{"origin": [14, -4, 19], "size": [1, 1, 8], "uv": [0, 2]},
						{"origin": [33, -4, 19], "size": [1, 1, 8], "uv": [12, 44]},
						{"origin": [34, -3, 19], "size": [1, 1, 8], "uv": [18, 19]},
						{"origin": [35, -2, 19], "size": [1, 1, 8], "uv": [16, 9]},
						{"origin": [36, -1, 19], "size": [1, 1, 8], "uv": [24, 33]},
						{"origin": [36, 20, 19], "size": [1, 1, 8], "uv": [0, 2]},
						{"origin": [35, 21, 19], "size": [1, 1, 8], "uv": [4, 7]},
						{"origin": [34, 22, 19], "size": [1, 1, 8], "uv": [0, 0]},
						{"origin": [13, 22, 19], "size": [1, 1, 8], "uv": [0, 0]},
						{"origin": [12, 21, 19], "size": [1, 1, 8], "uv": [1, 9]},
						{"origin": [11, 20, 19], "size": [1, 1, 8], "uv": [2, 12]},
						{"origin": [11, -1, 19], "size": [1, 1, 8], "uv": [84, 69]},
						{"origin": [12, -2, 19], "size": [1, 1, 8], "uv": [71, 37]},
						{"origin": [13, -3, 19], "size": [1, 1, 8], "uv": [14, 16]},
						{"origin": [33, 23, 19], "size": [1, 1, 8], "uv": [13, 9]},
						{"origin": [14, 23, 19], "size": [1, 1, 8], "uv": [0, 0]},
						{"origin": [10, 19, 19], "size": [1, 1, 8], "uv": [0, 0]},
						{"origin": [10, 0, 19], "size": [1, 1, 8], "uv": [0, 0]},
						{"origin": [37, 0, 19], "size": [1, 1, 8], "uv": [0, 0]},
						{"origin": [37, 19, 19], "size": [1, 1, 8], "uv": [0, 3]},
						{"origin": [39, 14, 20], "size": [1, 1, 6], "uv": [0, 0]},
						{"origin": [39, 6, 19], "size": [1, 8, 8], "uv": [0, 0]},
						{"origin": [39, 7, 27], "size": [1, 6, 1], "uv": [0, 0]},
						{"origin": [39, 7, 18], "size": [1, 6, 1], "uv": [0, 0]},
						{"origin": [8, 7, 18], "size": [1, 6, 1], "uv": [0, 0]},
						{"origin": [8, 7, 27], "size": [1, 6, 1], "uv": [0, 0]},
						{"origin": [19, 7, 38], "size": [1, 6, 1], "uv": [0, 0]},
						{"origin": [11, 8, 34], "size": [1, 4, 1], "uv": [0, 0]},
						{"origin": [12, 8, 35], "size": [1, 4, 1], "uv": [0, 0]},
						{"origin": [35, 8, 35], "size": [1, 4, 1], "uv": [0, 0]},
						{"origin": [36, 8, 34], "size": [1, 4, 1], "uv": [0, 0]},
						{"origin": [36, 8, 11], "size": [1, 4, 1], "uv": [0, 0]},
						{"origin": [35, 8, 10], "size": [1, 4, 1], "uv": [0, 0]},
						{"origin": [12, 8, 10], "size": [1, 4, 1], "uv": [0, 0]},
						{"origin": [11, 8, 11], "size": [1, 4, 1], "uv": [0, 0]},
						{"origin": [17, 6, 37], "size": [1, 8, 1], "uv": [0, 0]},
						{"origin": [15, 4, 36], "size": [1, 12, 1], "uv": [0, 0]},
						{"origin": [15, 4, 9], "size": [1, 12, 1], "uv": [0, 0]},
						{"origin": [32, 4, 9], "size": [1, 12, 1], "uv": [0, 0]},
						{"origin": [37, 4, 14], "size": [1, 12, 1], "uv": [0, 0]},
						{"origin": [37, 4, 31], "size": [1, 12, 1], "uv": [0, 0]},
						{"origin": [36, 2, 31], "size": [1, 16, 1], "uv": [0, 0]},
						{"origin": [34, 1, 32], "size": [2, 18, 1], "uv": [0, 0]},
						{"origin": [34, 2, 33], "size": [1, 16, 1], "uv": [0, 0]},
						{"origin": [33, 1, 33], "size": [1, 18, 2], "uv": [0, 0]},
						{"origin": [32, 2, 35], "size": [1, 16, 1], "uv": [0, 0]},
						{"origin": [15, 2, 35], "size": [1, 16, 1], "uv": [0, 0]},
						{"origin": [14, 1, 33], "size": [1, 18, 2], "uv": [0, 0]},
						{"origin": [13, 2, 33], "size": [1, 16, 1], "uv": [0, 0]},
						{"origin": [12, 1, 32], "size": [2, 18, 1], "uv": [0, 0]},
						{"origin": [11, 2, 31], "size": [1, 16, 1], "uv": [0, 0]},
						{"origin": [11, 2, 14], "size": [1, 16, 1], "uv": [0, 0]},
						{"origin": [12, 1, 13], "size": [2, 18, 1], "uv": [16, 169]},
						{"origin": [13, 2, 12], "size": [1, 16, 1], "uv": [17, 176]},
						{"origin": [14, 1, 11], "size": [1, 18, 2], "uv": [10, 171]},
						{"origin": [15, 2, 10], "size": [1, 16, 1], "uv": [40, 172]},
						{"origin": [32, 2, 10], "size": [1, 16, 1], "uv": [0, 0]},
						{"origin": [33, 1, 11], "size": [1, 18, 2], "uv": [0, 0]},
						{"origin": [34, 2, 12], "size": [1, 16, 1], "uv": [0, 0]},
						{"origin": [34, 1, 13], "size": [2, 18, 1], "uv": [0, 0]},
						{"origin": [36, 2, 14], "size": [1, 16, 1], "uv": [0, 0]},
						{"origin": [32, 4, 36], "size": [1, 12, 1], "uv": [0, 0]},
						{"origin": [10, 4, 31], "size": [1, 12, 1], "uv": [0, 0]},
						{"origin": [10, 4, 14], "size": [1, 12, 1], "uv": [0, 0]},
						{"origin": [11, 4, 13], "size": [1, 12, 1], "uv": [0, 0]},
						{"origin": [12, 4, 12], "size": [1, 12, 1], "uv": [0, 0]},
						{"origin": [13, 4, 11], "size": [1, 12, 1], "uv": [0, 0]},
						{"origin": [14, 4, 10], "size": [1, 12, 1], "uv": [0, 0]},
						{"origin": [33, 4, 10], "size": [1, 12, 1], "uv": [0, 0]},
						{"origin": [34, 4, 11], "size": [1, 12, 1], "uv": [0, 0]},
						{"origin": [35, 4, 12], "size": [1, 12, 1], "uv": [0, 0]},
						{"origin": [36, 4, 13], "size": [1, 12, 1], "uv": [0, 0]},
						{"origin": [36, 4, 32], "size": [1, 12, 1], "uv": [0, 0]},
						{"origin": [35, 4, 33], "size": [1, 12, 1], "uv": [0, 0]},
						{"origin": [34, 4, 34], "size": [1, 12, 1], "uv": [0, 0]},
						{"origin": [33, 4, 35], "size": [1, 12, 1], "uv": [0, 0]},
						{"origin": [14, 4, 35], "size": [1, 12, 1], "uv": [0, 0]},
						{"origin": [13, 4, 34], "size": [1, 12, 1], "uv": [0, 0]},
						{"origin": [12, 4, 33], "size": [1, 12, 1], "uv": [0, 0]},
						{"origin": [11, 4, 32], "size": [1, 12, 1], "uv": [0, 0]},
						{"origin": [30, 6, 37], "size": [1, 8, 1], "uv": [0, 0]},
						{"origin": [30, 6, 8], "size": [1, 8, 1], "uv": [0, 0]},
						{"origin": [33, 6, 9], "size": [1, 8, 1], "uv": [0, 0]},
						{"origin": [33, 6, 36], "size": [1, 8, 1], "uv": [0, 0]},
						{"origin": [14, 6, 36], "size": [1, 8, 1], "uv": [0, 0]},
						{"origin": [14, 6, 9], "size": [1, 8, 1], "uv": [0, 0]},
						{"origin": [17, 6, 8], "size": [1, 8, 1], "uv": [0, 0]},
						{"origin": [9, 6, 16], "size": [1, 8, 1], "uv": [0, 0]},
						{"origin": [9, 6, 29], "size": [1, 8, 1], "uv": [0, 0]},
						{"origin": [38, 6, 29], "size": [1, 8, 1], "uv": [0, 0]},
						{"origin": [37, 6, 32], "size": [1, 8, 1], "uv": [0, 0]},
						{"origin": [37, 6, 13], "size": [1, 8, 1], "uv": [0, 0]},
						{"origin": [10, 6, 13], "size": [1, 8, 1], "uv": [0, 0]},
						{"origin": [10, 6, 32], "size": [1, 8, 1], "uv": [0, 0]},
						{"origin": [11, 6, 33], "size": [1, 8, 1], "uv": [0, 0]},
						{"origin": [12, 6, 34], "size": [1, 8, 1], "uv": [0, 0]},
						{"origin": [13, 6, 35], "size": [1, 8, 1], "uv": [0, 0]},
						{"origin": [13, 6, 10], "size": [1, 8, 1], "uv": [0, 0]},
						{"origin": [12, 6, 11], "size": [1, 8, 1], "uv": [0, 0]},
						{"origin": [11, 6, 12], "size": [1, 8, 1], "uv": [0, 0]},
						{"origin": [36, 6, 12], "size": [1, 8, 1], "uv": [0, 0]},
						{"origin": [35, 6, 11], "size": [1, 8, 1], "uv": [0, 0]},
						{"origin": [34, 6, 10], "size": [1, 8, 1], "uv": [0, 0]},
						{"origin": [34, 6, 35], "size": [1, 8, 1], "uv": [0, 0]},
						{"origin": [35, 6, 34], "size": [1, 8, 1], "uv": [0, 0]},
						{"origin": [36, 6, 33], "size": [1, 8, 1], "uv": [0, 0]},
						{"origin": [38, 6, 16], "size": [1, 8, 1], "uv": [0, 0]},
						{"origin": [28, 7, 38], "size": [1, 6, 1], "uv": [0, 0]},
						{"origin": [28, 7, 7], "size": [1, 6, 1], "uv": [0, 0]},
						{"origin": [19, 7, 7], "size": [1, 6, 1], "uv": [0, 0]},
						{"origin": [20, 6, 7], "size": [8, 8, 1], "uv": [0, 0]},
						{"origin": [20, 6, 38], "size": [8, 8, 1], "uv": [0, 0]},
						{"origin": [18, 4, 37], "size": [12, 12, 1], "uv": [0, 0]},
						{"origin": [18, 4, 8], "size": [12, 12, 1], "uv": [0, 0]},
						{"origin": [16, 2, 9], "size": [16, 16, 1], "uv": [67, 184]},
						{"origin": [15, 0, 11], "size": [18, 19, 2], "inflate": 0.01, "uv": [50, 176]},
						{"origin": [16, 2, 36], "size": [16, 16, 1], "uv": [0, 0]},
						{"origin": [15, 0, 33], "size": [18, 19, 2], "uv": [0, 0]},
						{"origin": [21, 14, 38], "size": [6, 1, 1], "uv": [0, 0]},
						{"origin": [21, 5, 38], "size": [6, 1, 1], "uv": [0, 0]},
						{"origin": [21, 5, 7], "size": [6, 1, 1], "uv": [0, 0]},
						{"origin": [20, 3, 8], "size": [8, 1, 1], "uv": [0, 0]},
						{"origin": [20, 16, 8], "size": [8, 1, 1], "uv": [0, 0]},
						{"origin": [20, 16, 37], "size": [8, 1, 1], "uv": [0, 0]},
						{"origin": [18, 18, 36], "size": [12, 1, 1], "uv": [0, 3]},
						{"origin": [18, 1, 36], "size": [12, 1, 1], "uv": [16, 17]},
						{"origin": [18, 1, 9], "size": [12, 1, 1], "uv": [9, 16]},
						{"origin": [18, 18, 9], "size": [12, 1, 1], "uv": [0, 0]},
						{"origin": [18, 23, 14], "size": [12, 1, 1], "uv": [0, 0]},
						{"origin": [18, 23, 31], "size": [12, 1, 1], "uv": [0, 0]},
						{"origin": [18, -4, 31], "size": [12, 1, 1], "uv": [0, 0]},
						{"origin": [18, -4, 14], "size": [12, 1, 1], "uv": [0, 0]},
						{"origin": [18, -3, 13], "size": [12, 1, 1], "uv": [0, 0]},
						{"origin": [18, -2, 12], "size": [12, 1, 1], "uv": [6, 17]},
						{"origin": [18, -1, 11], "size": [12, 1, 1], "uv": [0, 0]},
						{"origin": [18, 0, 10], "size": [12, 1, 1], "uv": [0, 0]},
						{"origin": [18, 19, 10], "size": [12, 1, 1], "uv": [0, 0]},
						{"origin": [18, 20, 11], "size": [12, 1, 1], "uv": [21, 18]},
						{"origin": [18, 21, 12], "size": [12, 1, 1], "uv": [0, 0]},
						{"origin": [18, 22, 13], "size": [12, 1, 1], "uv": [0, 0]},
						{"origin": [18, 22, 32], "size": [12, 1, 1], "uv": [13, 19]},
						{"origin": [18, 21, 33], "size": [12, 1, 1], "uv": [20, 18]},
						{"origin": [18, 20, 34], "size": [12, 1, 1], "uv": [0, 0]},
						{"origin": [18, 19, 35], "size": [12, 1, 1], "uv": [0, 0]},
						{"origin": [18, 0, 35], "size": [12, 1, 1], "uv": [0, 0]},
						{"origin": [16, 1, 35], "size": [16, 1, 1], "uv": [0, 0]},
						{"origin": [15, 0, 33], "size": [17, 1, 2], "inflate": 0.01, "uv": [0, 0]},
						{"origin": [16, -1, 33], "size": [16, 1, 1], "uv": [0, 0]},
						{"origin": [15, -2, 32], "size": [18, 2, 1], "uv": [9, 17]},
						{"origin": [16, -3, 31], "size": [16, 1, 1], "uv": [0, 0]},
						{"origin": [16, -3, 14], "size": [16, 1, 1], "uv": [0, 0]},
						{"origin": [16, -3, 14], "size": [16, 1, 1], "uv": [0, 0]},
						{"origin": [15, -2, 13], "size": [18, 2, 1], "uv": [0, 0]},
						{"origin": [16, -1, 12], "size": [16, 1, 1], "uv": [0, 0]},
						{"origin": [16, 0, 11], "size": [16, 1, 2], "uv": [0, 0]},
						{"origin": [16, 1, 10], "size": [16, 1, 1], "uv": [64, 204]},
						{"origin": [16, 18, 10], "size": [16, 1, 1], "uv": [0, 0]},
						{"origin": [15, 19, 11], "size": [18, 1, 2], "uv": [0, 0]},
						{"origin": [16, 20, 12], "size": [16, 1, 1], "uv": [0, 0]},
						{"origin": [15, 20, 13], "size": [18, 2, 1], "uv": [0, 17]},
						{"origin": [16, 22, 14], "size": [16, 1, 1], "uv": [0, 0]},
						{"origin": [16, 22, 31], "size": [16, 1, 1], "uv": [0, 0]},
						{"origin": [15, 20, 32], "size": [18, 2, 1], "uv": [0, 0]},
						{"origin": [16, 20, 33], "size": [16, 1, 1], "uv": [0, 0]},
						{"origin": [15, 19, 33], "size": [18, 1, 2], "uv": [0, 0]},
						{"origin": [16, 18, 35], "size": [16, 1, 1], "uv": [0, 0]},
						{"origin": [18, -1, 34], "size": [12, 1, 1], "uv": [8, 17]},
						{"origin": [18, -2, 33], "size": [12, 1, 1], "uv": [0, 0]},
						{"origin": [18, -3, 32], "size": [12, 1, 1], "uv": [0, 0]},
						{"origin": [20, 3, 37], "size": [8, 1, 1], "uv": [0, 0]},
						{"origin": [20, 24, 29], "size": [8, 1, 1], "uv": [0, 0]},
						{"origin": [20, 24, 16], "size": [8, 1, 1], "uv": [0, 0]},
						{"origin": [20, -5, 16], "size": [8, 1, 1], "uv": [0, 2]},
						{"origin": [20, -4, 13], "size": [8, 1, 1], "uv": [0, 2]},
						{"origin": [20, -3, 12], "size": [8, 1, 1], "uv": [0, 0]},
						{"origin": [20, -2, 11], "size": [8, 1, 1], "uv": [0, 0]},
						{"origin": [20, -1, 10], "size": [8, 1, 1], "uv": [0, 9]},
						{"origin": [20, 20, 10], "size": [8, 1, 1], "uv": [1, 4]},
						{"origin": [20, 21, 11], "size": [8, 1, 1], "uv": [16, 19]},
						{"origin": [20, 22, 12], "size": [8, 1, 1], "uv": [2, 17]},
						{"origin": [20, 22, 33], "size": [8, 1, 1], "uv": [0, 0]},
						{"origin": [20, 21, 34], "size": [8, 1, 1], "uv": [17, 18]},
						{"origin": [20, 20, 35], "size": [8, 1, 1], "uv": [53, 19]},
						{"origin": [20, -1, 35], "size": [8, 1, 1], "uv": [6, 17]},
						{"origin": [20, -2, 34], "size": [8, 1, 1], "uv": [0, 0]},
						{"origin": [20, -3, 33], "size": [8, 1, 1], "uv": [12, 18]},
						{"origin": [20, -4, 32], "size": [8, 1, 1], "uv": [0, 0]},
						{"origin": [20, 0, 36], "size": [8, 1, 1], "uv": [0, 0]},
						{"origin": [20, 0, 9], "size": [8, 1, 1], "uv": [13, 26]},
						{"origin": [20, 19, 9], "size": [8, 1, 1], "uv": [0, 0]},
						{"origin": [20, 19, 36], "size": [8, 1, 1], "uv": [0, 0]},
						{"origin": [20, 23, 32], "size": [8, 1, 1], "uv": [11, 12]},
						{"origin": [20, 23, 13], "size": [8, 1, 1], "uv": [0, 0]},
						{"origin": [20, -5, 29], "size": [8, 1, 1], "uv": [0, 0]},
						{"origin": [21, 14, 7], "size": [6, 1, 1], "uv": [0, 0]},
						{"origin": [14, 0, 12], "size": [20, 20, 22], "inflate": 0.02, "uv": [166, 166]},
						{"origin": [13, 0, 13], "size": [22, 20, 20], "inflate": 0.02, "uv": [162, 154]},
						{"origin": [14, -1, 13], "size": [20, 22, 20], "inflate": 0.03, "uv": [0, 138]}
					]
				}
			]
		}
	]
}